geovista/__init__.py
geovista/__init__.pyi
geovista/__main__.py
geovista/_version.py
geovista/bridge.py
geovista/cli.py
geovista/common.py
geovista/config.py
geovista/core.py
geovista/crs.py
geovista/filters.py
geovista/geodesic.py
geovista/geometry.py
geovista/geoplotter.py
geovista/gridlines.py
geovista/qt.py
geovista/raster.py
geovista/report.py
geovista/search.py
geovista/theme.py
geovista/transform.py
geovista/cache/README.md
geovista/cache/__init__.py
geovista/cache/registry.txt
geovista/examples/README.rst
geovista/examples/__init__.py
geovista/examples/clouds.py
geovista/examples/clouds_robin.py
geovista/examples/curvilinear/README.rst
geovista/examples/curvilinear/__init__.py
geovista/examples/curvilinear/from_2d__orca.py
geovista/examples/curvilinear/from_2d__orca_moll.py
geovista/examples/point_cloud/README.rst
geovista/examples/point_cloud/__init__.py
geovista/examples/point_cloud/from_points__orca_cloud.py
geovista/examples/point_cloud/from_points__orca_cloud_eqc.py
geovista/examples/rectilinear/README.rst
geovista/examples/rectilinear/__init__.py
geovista/examples/rectilinear/from_1d__oisst.py
geovista/examples/rectilinear/from_1d__oisst_eqc.py
geovista/examples/rectilinear/from_1d__synthetic_face_m1_n1.py
geovista/examples/rectilinear/from_1d__synthetic_face_m1_n1_robin.py
geovista/examples/rectilinear/from_1d__synthetic_node_m1_n1.py
geovista/examples/rectilinear/from_1d__synthetic_node_m1_n1_moll.py
geovista/examples/rectilinear/from_2d__synthetic_face_m1n1.py
geovista/examples/rectilinear/from_2d__synthetic_face_m1n1_robin.py
geovista/examples/rectilinear/from_2d__synthetic_node_m1n1.py
geovista/examples/rectilinear/from_2d__synthetic_node_m1n1_moll.py
geovista/examples/scalar_data/README.rst
geovista/examples/scalar_data/__init__.py
geovista/examples/scalar_data/earthquakes.py
geovista/examples/scalar_data/earthquakes_wink1.py
geovista/examples/scalar_data/from_tiff__dem.py
geovista/examples/scalar_data/from_tiff__rgb.py
geovista-0.5.3.dist-info/LICENSE
geovista-0.5.3.dist-info/METADATA
geovista-0.5.3.dist-info/WHEEL
geovista-0.5.3.dist-info/entry_points.txt
geovista-0.5.3.dist-info/top_level.txt
geovista-0.5.3.dist-info/RECORD
