Metadata-Version: 2.1
Name: geovista
Version: 0.5.3
Summary: Cartographic rendering and mesh analytics powered by PyVista
Author-email: GeoVista Contributors <geovista.pub@gmail.com>
License: BSD 3-Clause License
Project-URL: Code, https://github.com/bjlittle/geovista
Project-URL: Discussions, https://github.com/bjlittle/geovista/discussions
Project-URL: Documentation, https://geovista.readthedocs.io
Project-URL: Issues, https://github.com/bjlittle/geovista/issues
Keywords: cartography,curvilinear,earth-science,grid,mesh,python,pyvista,rectilinear,ugrid,unstructured,vtk
Classifier: Development Status :: 1 - Planning
Classifier: Intended Audience :: Science/Research
Classifier: License :: OSI Approved :: BSD License
Classifier: Natural Language :: English
Classifier: Operating System :: OS Independent
Classifier: Programming Language :: Python :: 3 :: Only
Classifier: Programming Language :: Python :: 3.10
Classifier: Programming Language :: Python :: 3.11
Classifier: Programming Language :: Python :: 3.12
Classifier: Topic :: Scientific/Engineering :: Atmospheric Science
Requires-Python: >=3.10
License-File: LICENSE
Requires-Dist: cartopy >=0.22
Requires-Dist: click
Requires-Dist: click-default-group
Requires-Dist: cmocean
Requires-Dist: lazy-loader
Requires-Dist: netCDF4
Requires-Dist: numpy >=1.24
Requires-Dist: platformdirs
Requires-Dist: pooch
Requires-Dist: pykdtree
Requires-Dist: pyproj >=3.3
Requires-Dist: pyvista >=0.43.1
Provides-Extra: cmap
Requires-Dist: colorcet ; extra == 'cmap'
Provides-Extra: docs
Requires-Dist: ipykernel ; extra == 'docs'
Requires-Dist: myst-nb ; extra == 'docs'
Requires-Dist: numpydoc ; extra == 'docs'
Requires-Dist: sphinx >=7.3 ; extra == 'docs'
Requires-Dist: sphinx-design ; extra == 'docs'
Requires-Dist: sphinx-autoapi ; extra == 'docs'
Requires-Dist: sphinx-book-theme >=1.1.3 ; extra == 'docs'
Requires-Dist: sphinx-click ; extra == 'docs'
Requires-Dist: sphinx-copybutton ; extra == 'docs'
Requires-Dist: sphinx-gallery >=0.16 ; extra == 'docs'
Requires-Dist: sphinx-tags ; extra == 'docs'
Requires-Dist: sphinx-tippy ; extra == 'docs'
Requires-Dist: sphinx-togglebutton ; extra == 'docs'
Requires-Dist: pydata-sphinx-theme >=0.15.3 ; extra == 'docs'
Requires-Dist: ipywidgets ; extra == 'docs'
Requires-Dist: jupyter-server-proxy ; extra == 'docs'
Requires-Dist: nest-asyncio ; extra == 'docs'
Requires-Dist: trame ; extra == 'docs'
Requires-Dist: trame-client ; extra == 'docs'
Requires-Dist: trame-server ; extra == 'docs'
Requires-Dist: trame-vtk ; extra == 'docs'
Requires-Dist: trame-vuetify ; extra == 'docs'
Provides-Extra: exam
Requires-Dist: fastparquet ; extra == 'exam'
Requires-Dist: h3 >=4.1 ; extra == 'exam'
Requires-Dist: pandas ; extra == 'exam'
Requires-Dist: pyarrow ; extra == 'exam'
Requires-Dist: rasterio >=1.3 ; extra == 'exam'
Provides-Extra: test
Requires-Dist: codecov ; extra == 'test'
Requires-Dist: pre-commit ; extra == 'test'
Requires-Dist: pytest >=6.0 ; extra == 'test'
Requires-Dist: pytest-cov ; extra == 'test'
Requires-Dist: pytest-mock ; extra == 'test'
Requires-Dist: pytest-pyvista ; extra == 'test'
Requires-Dist: pytest-xvfb ; extra == 'test'
